ag_utils-0.0.8.dist-info/licenses/LICENSE
agutils/__init__.py
agutils/annotatable.py
agutils/annotatable.pyi
agutils/classproperty.py
agutils/colored_message.py
agutils/decorator_injector.py
agutils/decorator_injector.pyi
agutils/env_var.py
agutils/immutable.py
agutils/immutable.pyi
agutils/interface.py
agutils/interface.pyi
agutils/logger_meta.py
agutils/logger_meta.pyi
ag_utils-0.0.8.dist-info/METADATA
ag_utils-0.0.8.dist-info/WHEEL
ag_utils-0.0.8.dist-info/top_level.txt
ag_utils-0.0.8.dist-info/RECORD
