Metadata-Version: 2.4
Name: ag-utils
Version: 0.0.8
Summary: Utilities for different jobs
Author-email: Alexandr Kozlov <alex.gadfly@gmail.com>
License-Expression: MIT
Project-URL: Homepage, https://gitlab.com/alexandrgadfly/python-utils
Classifier: Programming Language :: Python :: 3
Classifier: Operating System :: OS Independent
Requires-Python: >=3.9
License-File: LICENSE
Dynamic: license-file
